{
  "project_info": {
    "project_number": "271315539363",
    "project_id": "quran-chat-ae0c1",
    "storage_bucket": "quran-chat-ae0c1.firebasestorage.app"
  },
  "client": [
    {
      "client_info": {
        "mobilesdk_app_id": "1:271315539363:android:baa0ff3681a54839527616",
        "android_client_info": {
          "package_name": "com.app.quranchat"
        }
      },
      "oauth_client": [],
      "api_key": [
        {
          "current_key": "AIzaSyCvSJGcZgwcoIZ5z7gEhppotKH5DapjkZc"
        }
      ],
      "services": {
        "appinvite_service": {
          "other_platform_oauth_client": []
        }
      }
    }
  ],
  "configuration_version": "1"
}